rnakinet/__init__.py
rnakinet/data_utils/__init__.py
rnakinet/data_utils/dataloading.py
rnakinet/data_utils/read_utils.py
rnakinet/data_utils/workers.py
rnakinet/models/__init__.py
rnakinet/models/model.py
rnakinet/models/model_experimental.py
rnakinet/models/rnakinet_r10.ckpt
rnakinet/models/rnakinet_r9.ckpt
rnakinet/scripts/__init__.py
rnakinet/scripts/inference.py
rnakinet/scripts/predict_halflives.py
rnakinet-1.0.0.dist-info/LICENSE.txt
rnakinet-1.0.0.dist-info/METADATA
rnakinet-1.0.0.dist-info/WHEEL
rnakinet-1.0.0.dist-info/entry_points.txt
rnakinet-1.0.0.dist-info/top_level.txt
rnakinet-1.0.0.dist-info/RECORD
