Metadata-Version: 2.1
Name: rnakinet
Version: 1.0.0
Summary: Package for predicting 5EU in nanopore reads and predicting RNA halflives
Home-page: https://github.com/maragkakislab/RNAkinet
Requires-Python: <3.11,>=3.8
License-File: LICENSE.txt
Requires-Dist: pandas
Requires-Dist: torch<=2.2,>=2.0
Requires-Dist: numpy==1.26.*
Requires-Dist: ont-fast5-api
Requires-Dist: scipy
Requires-Dist: scikit-learn
Requires-Dist: pysam
Requires-Dist: tqdm
